.travis.yml
AUTHORS
CHANGELOG
ChangeLog
README.md
requirements.txt
run_tests.sh
setup.cfg
setup.py
test-requirements.txt
bin/cloud-info-provider-service.py
cloud_bdii/__init__.py
cloud_bdii/core.py
cloud_bdii/exceptions.py
cloud_bdii/utils.py
cloud_bdii/providers/__init__.py
cloud_bdii/providers/opennebula.py
cloud_bdii/providers/openstack.py
cloud_bdii/providers/static.py
cloud_bdii/tests/__init__.py
cloud_bdii/tests/data.py
cloud_bdii/tests/one.imagepool.info.xml
cloud_bdii/tests/one.templatepool.info.xml
cloud_bdii/tests/test_base_provider.py
cloud_bdii/tests/test_core.py
cloud_bdii/tests/test_opennebula.py
cloud_bdii/tests/test_openstack.py
cloud_bdii/tests/test_static.py
cloud_bdii/tests/utils.py
cloud_bdii_provider.egg-info/PKG-INFO
cloud_bdii_provider.egg-info/SOURCES.txt
cloud_bdii_provider.egg-info/dependency_links.txt
cloud_bdii_provider.egg-info/entry_points.txt
cloud_bdii_provider.egg-info/not-zip-safe
cloud_bdii_provider.egg-info/requires.txt
cloud_bdii_provider.egg-info/top_level.txt
etc/sample.opennebula.yaml
etc/sample.opennebularocci.yaml
etc/sample.openstack.yaml
etc/sample.static.yaml
etc/templates/application_environment.ldif
etc/templates/bdii.ldif
etc/templates/clouddomain.ldif
etc/templates/compute_endpoint.ldif
etc/templates/compute_service.ldif
etc/templates/domain.ldif
etc/templates/execution_environment.ldif
etc/templates/headers.ldif
etc/templates/storage_capacity.ldif
etc/templates/storage_endpoint.ldif
etc/templates/storage_service.ldif
rpm/cloud-info-provider-service.spec