Metadata-Version: 1.1
Name: cloud-bdii-provider
Version: 0.4.dev140.g387348d
Summary: Cloud BDII info provider
Home-page: UNKNOWN
Author: Alvaro Lopez Garcia
Author-email: aloga@ifca.unican.es
License: UNKNOWN
Platform: UNKNOWN
Classifier: Intended Audience :: Information Technology
Classifier: Intended Audience :: System Administrators
Classifier: License :: OSI Approved :: Apache Software License
Classifier: Operating System :: POSIX :: Linux
Classifier: Programming Language :: Python
Classifier: Programming Language :: Python :: 2
Classifier: Programming Language :: Python :: 2.6
Classifier: Programming Language :: Python :: 2.7
Classifier: Topic :: System :: Monitoring
